setup.py
django_pipeline_cjsx.egg-info/PKG-INFO
django_pipeline_cjsx.egg-info/SOURCES.txt
django_pipeline_cjsx.egg-info/dependency_links.txt
django_pipeline_cjsx.egg-info/pbr.json
django_pipeline_cjsx.egg-info/top_level.txt
pipeline_cjsx/__init__.py
pipeline_cjsx/compiler.py