Metadata-Version: 1.1
Name: django-pipeline-cjsx
Version: 0.1.0
Summary: 
